<?xml version="1.0"?><metadata><Esri><MetaID SYNC="true" /><CreaDate SYNC="true" /><CreaTime SYNC="true" /><SyncOnce SYNC="true">TRUE</SyncOnce><ModDate SYNC="true" /><ModTime SYNC="true" /></Esri><dataIdInfo><idCitation><resTitle sync="true">Create Referenced Mosaic Dataset (Data Management)</resTitle><citRespParty><rpIndName /><rpOrgName>ESRI, Inc.</rpOrgName><rpPosName /><rpCntInfo><cntAddress><delPoint>380 New York Street</delPoint><city>Redlands</city><adminArea>California</adminArea><postCode>92373 - 8100</postCode><eMailAdd>info@esri.com</eMailAdd><country>United States</country></cntAddress><cntPhone><voiceNum>909-793-2853</voiceNum><faxNum>909-793-5953</faxNum></cntPhone></rpCntInfo><role><RoleCd>010</RoleCd></role></citRespParty></idCitation><idAbs>
			<para>Creates a new mosaic dataset from an existing raster catalog, a selection set from a raster catalog, or a mosaic dataset.</para>
		</idAbs><descKeys KeyTypCd="005"><keyTyp><keyTyp>005</keyTyp></keyTyp><keyword>Amd</keyword><keyword>Mosaic Dataset</keyword><keyword>Raster Catalog</keyword></descKeys></dataIdInfo><distInfo><distributor><distorFormat><formatName sync="true">ArcToolBox Tool</formatName></distorFormat><distorTran><onLineSrc><linkage /><protocol /><onFunct><onFunctCd /></onFunct></onLineSrc></distorTran></distributor></distInfo><metainfo><metd Sync="TRUE" /></metainfo><mdDateSt Sync="TRUE" /><tool name="CreateReferencedMosaicDataset" displayname="Create Referenced Mosaic Dataset (Data Management)" toolboxalias="management" softwarerestriction="none"><summary>
			<para>Creates a new mosaic dataset from an existing raster catalog, a selection set from a raster catalog, or a mosaic dataset.</para>
		</summary><alink_name>CreateReferencedMosaicDataset_management</alink_name><parameters><param sync="true" name="in_dataset" displayname="Input Raster Catalog Or Mosaic Dataset" datatype="Mosaic Layer; Mosaic Dataset; Raster Catalog Layer" direction="Input" expression="in_dataset" type="Required"><pythonReference>
						<para>Path and name of the input raster catalog or mosaic dataset.</para>
					</pythonReference><dialogReference>
						<para>Path and name of the input raster catalog or mosaic dataset.</para>
					</dialogReference></param><param sync="true" name="out_mosaic_dataset" displayname="Output Mosaic Dataset" datatype="Mosaic Dataset" direction="Output" expression="out_mosaic_dataset" type="Required"><pythonReference>
						<para> The path and folder location or geodatabase where the mosaic dataset will be created. </para>
					</pythonReference><dialogReference>
						<para> The path and folder location or geodatabase where the mosaic dataset will be created. </para>
					</dialogReference></param><param sync="true" name="coordinate_system" displayname="Coordinate System" datatype="Spatial Reference" direction="Input" expression="coordinate_system" type="Optional"><pythonReference>
						<para>The coordinate system defined for the mosaic dataset, which will be used for all the associated files created.</para>
					</pythonReference><dialogReference>
						<para>The coordinate system defined for the mosaic dataset, which will be used for all the associated files created.</para>
					</dialogReference></param><param sync="true" name="number_of_bands" displayname="Number Of Bands" datatype="Long" direction="Input" expression="number_of_bands" type="Optional"><pythonReference>
						<para>The number of raster dataset bands supported by the mosaic dataset.</para>
					</pythonReference><dialogReference>
						<para>The number of raster dataset bands supported by the mosaic dataset.</para>
					</dialogReference></param><param sync="true" name="pixel_type" displayname="Pixel Type" datatype="String" direction="Input" expression="pixel_type" type="Optional"><pythonReference>
						<para> The bit depth of a cell, used to determine the range of values that the mosaic dataset outputs. For example, an 8-bit mosaic dataset can have 256 unique pixel values, which range from 0 to 255. </para>
						<para>If it is not defined, it will be taken from the first raster dataset.</para>
						<bulletList><bullet_item>1_BIT—A 1-bit unsigned integer. The values can be 0 or 1. </bullet_item><bullet_item>2_BIT—A 2-bit unsigned integer. The values supported can be from 0 to 3. </bullet_item><bullet_item>4_BIT—A 4-bit unsigned integer. The values supported can be from 0 to 15. </bullet_item><bullet_item>8_BIT_UNSIGNED—An unsigned 8-bit data type. The values supported can be from 0 to 255.</bullet_item><bullet_item>8_BIT_SIGNED—A signed 8-bit data type. The values supported can be from -128 to 127.</bullet_item><bullet_item>16_BIT_UNSIGNED—A 16-bit unsigned data type. The values can range from 0 to 65,535.</bullet_item><bullet_item>16_BIT_SIGNED—A 16-bit signed data type. The values can range from -32,768 to 32,767.</bullet_item><bullet_item>32_BIT_UNSIGNED—A 32-bit unsigned data type. The values can range from 0 to 4,294,967,295. </bullet_item><bullet_item>32_BIT_SIGNED—A 32-bit signed data type. The values can range from -2,147,483,648 to 2,147,483,647.</bullet_item><bullet_item>32_BIT_FLOAT—A 32-bit data type supporting decimals. </bullet_item><bullet_item>64_BIT—A 64-bit data type supporting decimals.</bullet_item></bulletList>
					</pythonReference><dialogReference>
						<para> The bit depth of a cell, used to determine the range of values that the mosaic dataset outputs. For example, an 8-bit mosaic dataset can have 256 unique pixel values, which range from 0 to 255. </para>
						<para>If it is not defined, it will be taken from the first raster dataset.</para>
						<bulletList><bullet_item>1_BIT—A 1-bit unsigned integer. The values can be 0 or 1. </bullet_item><bullet_item>2_BIT—A 2-bit unsigned integer. The values supported can be from 0 to 3. </bullet_item><bullet_item>4_BIT—A 4-bit unsigned integer. The values supported can be from 0 to 15. </bullet_item><bullet_item>8_BIT_UNSIGNED—An unsigned 8-bit data type. The values supported can be from 0 to 255.</bullet_item><bullet_item>8_BIT_SIGNED—A signed 8-bit data type. The values supported can be from -128 to 127.</bullet_item><bullet_item>16_BIT_UNSIGNED—A 16-bit unsigned data type. The values can range from 0 to 65,535.</bullet_item><bullet_item>16_BIT_SIGNED—A 16-bit signed data type. The values can range from -32,768 to 32,767.</bullet_item><bullet_item>32_BIT_UNSIGNED—A 32-bit unsigned data type. The values can range from 0 to 4,294,967,295. </bullet_item><bullet_item>32_BIT_SIGNED—A 32-bit signed data type. The values can range from -2,147,483,648 to 2,147,483,647.</bullet_item><bullet_item>32_BIT_FLOAT—A 32-bit data type supporting decimals. </bullet_item><bullet_item>64_BIT—A 64-bit data type supporting decimals.</bullet_item></bulletList>
					</dialogReference></param><param sync="true" name="where_clause" displayname="Query Definition" datatype="SQL Expression" direction="Input" expression="where_clause" type="Optional"><pythonReference>
						<para>Use SQL to define a query, or use the Query Builder to build a query that identifies the raster datasets to be added to the mosaic dataset from the raster catalog or mosaic definition.</para>
					</pythonReference><dialogReference>
						<para>Use SQL to define a query, or use the Query Builder to build a query that identifies the raster datasets to be added to the mosaic dataset from the raster catalog or mosaic definition.</para>
					</dialogReference></param><param sync="true" name="in_template_dataset" displayname="Extent From Dataset" datatype="Extent" direction="Input" expression="in_template_dataset" type="Optional"><pythonReference>
						<para> Uses the extent of the specified raster dataset or feature class to define the extent of the raster datasets used in the mosaic dataset from the raster catalog or mosaic dataset. </para>
						<para> Rasters that lay along the defined extent will be included in the mosaic dataset.</para>
						<para>The input is not limited to a polygon feature class. </para>
					</pythonReference><dialogReference>
						<para> Uses the extent of the specified raster dataset or feature class to define the extent of the raster datasets used in the mosaic dataset from the raster catalog or mosaic dataset. </para>
						<para> Rasters that lay along the defined extent will be included in the mosaic dataset.</para>
						<para>The input is not limited to a polygon feature class. </para>
					</dialogReference></param><param sync="true" name="extent" displayname="Extent" datatype="Envelope" direction="Input" expression="extent" type="Optional"><pythonReference>
						<para>
The minimum and maximum x- and y-coordinates used to define the rectangular extent 
of the raster datasets used in the mosaic dataset from the raster catalog or mosaic dataset.</para>
					</pythonReference><dialogReference>
						<para>
The minimum and maximum x- and y-coordinates used to define the rectangular extent 
of the raster datasets used in the mosaic dataset from the raster catalog or mosaic dataset.</para>
					</dialogReference></param><param sync="true" name="select_using_features" displayname="Using Input Geometry For Selection" datatype="Boolean" direction="Input" expression="select_using_features" type="Optional"><pythonReference>
						<para> If a feature class is specified, you can choose to limit the extent to its envelope or clipped to the feature.</para>
						<para>To use this, the input must be a polygon feature class.</para>
						<bulletList><bullet_item>SELECT_USING_FEATURES—The selection is based on the shape of the feature. This is the default.</bullet_item><bullet_item>NO_SELECT_USING_FEATURES—The selection is based on the extent of the data within the feature class.</bullet_item></bulletList>
					</pythonReference><dialogReference>
						<para> If a feature class is specified, you can choose to limit the extent to its envelope or to the shape of the feature. </para>
						<bulletList>
							<bullet_item>Checked—The selection is based on the shape of the feature. This is the default.</bullet_item>
							<bullet_item>Unchecked—The selection is based on the extent of the data within the feature class.</bullet_item>
						</bulletList>
					</dialogReference></param><param sync="true" name="lod_field" displayname="Scale Field" datatype="Field" direction="Input" expression="lod_field" type="Optional"><pythonReference>
						<para> A field in the raster catalog table defining the map scales at which the mosaic should be displayed; otherwise, a wire frame will be displayed. </para>
					</pythonReference><dialogReference>
						<para> A field in the raster catalog table defining the map scales at which the mosaic should be displayed; otherwise, a wire frame will be displayed. </para>
					</dialogReference></param><param sync="true" name="minPS_field" displayname="Minimum Cell Size Field" datatype="Field" direction="Input" expression="minPS_field" type="Optional"><pythonReference>
						<para> A field in the raster catalog table defining the minimum cell size of the raster at which the mosaic should be displayed; otherwise, a wire frame will be displayed.</para>
					</pythonReference><dialogReference>
						<para> A field in the raster catalog table defining the minimum cell size of the raster at which the mosaic should be displayed; otherwise, a wire frame will be displayed.</para>
					</dialogReference></param><param sync="true" name="maxPS_field" displayname="Maximum Cell Size Field" datatype="Field" direction="Input" expression="maxPS_field" type="Optional"><pythonReference>
						<para> A field in the raster catalog table defining the maximum cell size of the raster at which the mosaic should be displayed; otherwise, a wire frame will be displayed. </para>
					</pythonReference><dialogReference>
						<para> A field in the raster catalog table defining the maximum cell size of the raster at which the mosaic should be displayed; otherwise, a wire frame will be displayed. </para>
					</dialogReference></param><param sync="true" name="pixelsize" displayname="Maximum Visible Cell Size" datatype="Double" direction="Input" expression="pixelsize" type="Optional"><pythonReference>
						<para>The maximum cell size in which the mosaic will be displayed. If the mosaic is displayed above this resolution, a wire frame will be displayed.</para>
					</pythonReference><dialogReference>
						<para>The maximum cell size in which the mosaic will be displayed. If the mosaic is displayed above this resolution, a wire frame will be displayed.</para>
					</dialogReference></param><param sync="true" name="build_boundary" displayname="Build Boundary" datatype="Boolean" direction="Input" expression="build_boundary" type="Optional"><pythonReference>
						<para> Generates the boundary polygon for the mosaic dataset. By default, the boundary merges all the footprint polygons to create a single boundary representing the extent of the valid pixels.</para>
						<para>This is only available if the mosaic dataset is created within a geodatabase.</para>
						<bulletList><bullet_item>BUILD_BOUNDARY—The boundary will be generated or updated. This is the default. </bullet_item><bullet_item>NO_BOUNDARY— The boundary will not be generated.</bullet_item></bulletList>
					</pythonReference><dialogReference>
						<para> Generates the boundary polygon for the mosaic dataset. By default, the boundary merges all the footprint polygons to create a single boundary representing the extent of the valid pixels.</para>
						<para>This is only available if the mosaic dataset is created within a geodatabase.</para>
						<bulletList>
							<bullet_item>Checked—The boundary will be generated or updated. This is the default.</bullet_item>
							<bullet_item>Unchecked—The boundary will not be generated.</bullet_item>
						</bulletList>
					</dialogReference></param></parameters><returnvalues></returnvalues><environments><environment name="Output_extent" label="Output extent">
						
					</environment><environment name="Current_workspace" label="Current workspace"></environment><environment name="Scratch_workspace" label="Scratch workspace"></environment><environment name="Output_extent" label="Output extent"></environment><environment name="Output_Config_Keyword" label="Output Config Keyword"></environment><environment name="Output_spatial_grid_1_2_3" label="Output spatial grid 1 2 3"></environment></environments><usage><bullet_item>
				<para> This mosaic dataset can be created within or outside a geodatabase. When not created within a geodatabase, <bulletList>
						<bullet_item>A boundary will not be created.</bullet_item>
						<bullet_item>The file will have an .amd extension.</bullet_item>
					</bulletList></para>
			</bullet_item><bullet_item>
				<para> If the input is an RPF raster catalog created using Military Analyst, the Scale Field should be specified.</para>
			</bullet_item><bullet_item>
				<para>Overviews cannot be created for a referenced mosaic dataset.</para>
			</bullet_item><bullet_item>
				<para>A referenced mosaic dataset is one option for serving a raster catalog as an image service; however, you can also create a fully capable mosaic dataset from a raster catalog using the  followed by the  tool.</para>
			</bullet_item><bullet_item>
				<para>You may use this tool to create a mosaic dataset from another mosaic dataset, to create a mosaic dataset with a different output. For example, you may create one mosaic dataset with elevation data, then create another that will be used to produce a derived product, such as slope or hillshade.</para>
			</bullet_item></usage><scriptExamples><scriptExample><title>CreateReferencedMosaicDataset example 1 (Python window)</title>
					<para>This is a Python sample for CreateReferencedMosaicDataset.</para>
				<code xml:space="preserve">import arcpy
arcpy.CreateReferencedMosaicDataset_management("c:/workspace/input.gdb/md", \
                                               "c:/workspace/output.gdb/refMD", \
                                               "GCS_WGS_1984.prj", "1", "#", \
                                               "#","c:/temp/ref_md.shp", \
                                               "SELECT_USING_FEATURES", "#", \
                                               "#", "#", "#", "#", "NO_BOUNDARY")
                    </code></scriptExample><scriptExample><title>CreateReferencedMosaicDataset example 2 (stand-alone script)</title>
					<para>This is a Python script sample for CreateReferencedMosaicDataset.</para>
				<code xml:space="preserve">##===========================
##Create Referenced Mosaic Dataset
##Usage: CreateReferencedMosaicDataset_management input_dataset out_mosaic_dataset
##                                                {coordinate_system} {number_of_bands}
##                                                {1_BIT | 2_BIT | 4_BIT | 8_BIT_UNSIGNED
##                                                | 8_BIT_SIGNED | 16_BIT_UNSIGNED | 16_BIT_SIGNED
##                                                | 32_BIT_UNSIGNED | 32_BIT_SIGNED | 32_BIT_FLOAT
##                                                | 64_BIT} {where_clause} {in_template_dataset}
##                                                {extent} {SELECT_USING_FEATURES
##                                                | NO_SELECT_USING_FEATURES}
##                                                {lod_field} {minPS_field} {maxPS_field}
##                                                {pixelSize} {BUILD_BOUNDARY | NO_BOUNDARY}

try:
    import arcpy
    arcpy.env.workspace = "C:/Workspace"
    # Create Referenced Mosaic Dataset from existing Mosaic Dataset
    # Use shape file to clip the source mosaic dataset
    arcpy.CreateReferencedMosaicDataset_management("RefMD.gdb/md", "ref_md.amd",\
                                                   "GCS_WGS_1984.prj", "1", "#",\
                                                   "#", "ref_md.shp", "#", \
                                                   "SELECT_USING_FEATURES",
                                                   "#", "#", "#", "#", "NO_BOUNDARY")
    
    # Create Referenced Mosaic Dataset from unmanaged raster catalog  
    arcpy.CreateReferencedMosaicDataset_management("RefMD.gdb/rc", "RefMD.gdb/rc_md",\
                                                   "#", "3", "#", "OBJECTID=2", "#",\
                                                   "#", "#", "Scale", "minps", "maxps",\
                                                   "3", "BUILD_BOUNDARY")
    
except:
    print "Calculate Referenced Mosaic Dataset example failed."
    print arcpy.GetMessages()
                    </code></scriptExample></scriptExamples></tool></metadata>