<?xml version="1.0"?>
<metadata>
<Esri>
<MetaID SYNC="true" />
<CreaDate SYNC="true" />
<CreaTime SYNC="true" />
<SyncOnce SYNC="true">TRUE</SyncOnce>
<ModDate SYNC="true" />
<ModTime SYNC="true" />
</Esri>
<toolbox name="Parcel Fabric" alias="fabric">
<arcToolboxHelpPath>C:\Program Files\ArcGIS\Help\gp</arcToolboxHelpPath>
<summary>The Parcel Fabric toolbox contains tools that work with the internal feature classes and tables of a parcel fabric. Using the Parcel Fabric toolbox, you can migrate data to a  parcel fabric, upgrade an existing parcel fabric, and create layer and table views on the parcel fabric.</summary>
<toolsets>
<toolset name="Data Migration" />
<toolset name="Layers and Table Views" />
<toolset name="Parcel Fabric Management" />
</toolsets>
</toolbox>
<dataIdInfo>
<idCitation>
<resTitle sync="true">Parcel Fabric</resTitle>
<citRespParty>
<rpIndName />
<rpOrgName>ESRI, Inc.</rpOrgName>
<rpPosName />
<role>
<RoleCd>010</RoleCd>
</role>
<rpCntInfo>
<cntAddress>
<delPoint>380 New York Street</delPoint>
<city>Redlands</city>
<adminArea>California</adminArea>
<postCode>92373 - 8100</postCode>
<eMailAdd>info@esri.com</eMailAdd>
<country>United States</country>
</cntAddress>
<cntPhone>
<voiceNum>909-793-2853</voiceNum>
<faxNum>909-793-5953</faxNum>
</cntPhone>
</rpCntInfo>
</citRespParty>
</idCitation>
<idAbs>The Parcel Fabric toolbox contains tools that work with the internal feature classes and tables of a parcel fabric. Using the Parcel Fabric toolbox, you can migrate data to a  parcel fabric, upgrade an existing parcel fabric, and create layer and table views on the parcel fabric.</idAbs>
<descKeys KeyTypCd="005">
<keyTyp>
<keyTyp>005</keyTyp>
</keyTyp>
</descKeys>
<resConst>
<Consts>
<useLimit />
</Consts>
</resConst>
</dataIdInfo>
<distInfo>
<distributor>
<distorFormat>
<formatName sync="true">ArcToolBox Toolbox</formatName>
</distorFormat>
</distributor>
</distInfo>
<metainfo>
<metd Sync="TRUE" />
</metainfo>
<mdDateSt Sync="TRUE" />
</metadata>
