<ArrayOfGPEnvironment xsi:type='typens:ArrayOfGPEnvironment' xmlns:xsi='http://www.w3.org/2001/XMLSchema-instance' xmlns:xs='http://www.w3.org/2001/XMLSchema' xmlns:typens='http://www.esri.com/schemas/ArcGIS/9.2'><GPEnvironment xsi:type='typens:GPEnvironment'><Name>cellSize</Name><DisplayName>Cell Size</DisplayName><Category>Raster Analysis</Category><Value xsi:type='typens:GPSACellSize'></Value><DataTypeName xsi:type='typens:GPDataTypeName'><Name>GPSACellSize</Name><DisplayName>Cell Size</DisplayName><Description>Spatial analyst cell size data type</Description><Category>Data Type</Category><FactoryCLSID xsi:type='typens:UID'><UID xsi:type='xs:string'>{26F24DDD-E11A-4E0F-B2DF-F55B5298E2C5}</UID></FactoryCLSID></DataTypeName><DisplayOrder>1</DisplayOrder><ControlCLSID xsi:nil='true'/><ParamDependencyArray xsi:type='typens:ArrayOfString'></ParamDependencyArray></GPEnvironment><GPEnvironment xsi:type='typens:GPEnvironment'><Name>mask</Name><DisplayName>Mask</DisplayName><Category>Raster Analysis</Category><Value xsi:type='typens:GPRasterLayer'></Value><Domain xsi:type='typens:GPSAGeoDataDomain'><DataTypeArray xsi:type='typens:ArrayOfArrayOfGPDataTypeName'><ArrayOfGPDataTypeName xsi:type='typens:GPDataTypeName'><Name>DERasterDataset</Name><DisplayName>Raster Dataset</DisplayName><Description>Raster Dataset</Description><Category>Data Type</Category><FactoryCLSID xsi:type='typens:UID'><UID xsi:type='xs:string'>{F5B8BC0A-7E4A-4AB8-8671-88C43BA03BC7}</UID></FactoryCLSID></ArrayOfGPDataTypeName><ArrayOfGPDataTypeName xsi:type='typens:GPDataTypeName'><Name>DERasterBand</Name><DisplayName>Raster Band</DisplayName><Description>Raster Band</Description><Category>Data Type</Category><FactoryCLSID xsi:type='typens:UID'><UID xsi:type='xs:string'>{F5B8BC0A-7E4A-4AB8-8671-88C43BA03BC7}</UID></FactoryCLSID></ArrayOfGPDataTypeName><ArrayOfGPDataTypeName xsi:type='typens:GPDataTypeName'><Name>GPRasterLayer</Name><DisplayName>Raster Layer</DisplayName><Description>Raster Layer</Description><Category>Data Type</Category><FactoryCLSID xsi:type='typens:UID'><UID xsi:type='xs:string'>{E41CFD44-5741-4F2B-8ACE-1A49E146D329}</UID></FactoryCLSID></ArrayOfGPDataTypeName><ArrayOfGPDataTypeName xsi:type='typens:GPDataTypeName'><Name>GPRasterFormulated</Name><DisplayName>Formulated Raster</DisplayName><Description>Formulated Raster</Description><Category>Data Type</Category><FactoryCLSID xsi:type='typens:UID'><UID xsi:type='xs:string'>{E001DEFC-E935-4000-8B3B-CE497A5BD87C}</UID></FactoryCLSID></ArrayOfGPDataTypeName><ArrayOfGPDataTypeName xsi:type='typens:GPDataTypeName'><Name>DEFeatureClass</Name><DisplayName>Feature Class</DisplayName><Description>Feature Class</Description><Category>Data Type</Category><FactoryCLSID xsi:type='typens:UID'><UID xsi:type='xs:string'>{64A3EBFB-6DEC-45DF-86A5-5BE541C5DBB6}</UID></FactoryCLSID></ArrayOfGPDataTypeName><ArrayOfGPDataTypeName xsi:type='typens:GPDataTypeName'><Name>GPFeatureLayer</Name><DisplayName>Feature Layer</DisplayName><Description>Feature Layer</Description><Category>Data Type</Category><FactoryCLSID xsi:type='typens:UID'><UID xsi:type='xs:string'>{E41CFD44-5741-4F2B-8ACE-1A49E146D329}</UID></FactoryCLSID></ArrayOfGPDataTypeName></DataTypeArray><FieldTypeArray xsi:type='typens:ArrayOfString'><String>esriFieldTypeOID</String><String>esriFieldTypeSmallInteger</String><String>esriFieldTypeInteger</String><String>esriFieldTypeSingle</String><String>esriFieldTypeDouble</String><String>esriFieldTypeString</String><String>esriFieldTypeGeometry</String></FieldTypeArray><GeometryTypeArray xsi:type='typens:ArrayOfString'><String>esriGeometryPoint</String><String>esriGeometryPolygon</String><String>esriGeometryPolyline</String><String>esriGeometryMultipoint</String></GeometryTypeArray><CheckField>true</CheckField><DefaultFieldName></DefaultFieldName></Domain><DataTypeName xsi:type='typens:GPSAGeoDataTypeName'><GeoDataDomain xsi:type='typens:GPSAGeoDataDomain'><DataTypeArray xsi:type='typens:ArrayOfArrayOfGPDataTypeName'><ArrayOfGPDataTypeName xsi:type='typens:GPDataTypeName'><Name>DERasterDataset</Name><DisplayName>Raster Dataset</DisplayName><Description>Raster Dataset</Description><Category>Data Type</Category><FactoryCLSID xsi:type='typens:UID'><UID xsi:type='xs:string'>{F5B8BC0A-7E4A-4AB8-8671-88C43BA03BC7}</UID></FactoryCLSID></ArrayOfGPDataTypeName><ArrayOfGPDataTypeName xsi:type='typens:GPDataTypeName'><Name>DERasterBand</Name><DisplayName>Raster Band</DisplayName><Description>Raster Band</Description><Category>Data Type</Category><FactoryCLSID xsi:type='typens:UID'><UID xsi:type='xs:string'>{F5B8BC0A-7E4A-4AB8-8671-88C43BA03BC7}</UID></FactoryCLSID></ArrayOfGPDataTypeName><ArrayOfGPDataTypeName xsi:type='typens:GPDataTypeName'><Name>GPRasterLayer</Name><DisplayName>Raster Layer</DisplayName><Description>Raster Layer</Description><Category>Data Type</Category><FactoryCLSID xsi:type='typens:UID'><UID xsi:type='xs:string'>{E41CFD44-5741-4F2B-8ACE-1A49E146D329}</UID></FactoryCLSID></ArrayOfGPDataTypeName><ArrayOfGPDataTypeName xsi:type='typens:GPDataTypeName'><Name>GPRasterFormulated</Name><DisplayName>Formulated Raster</DisplayName><Description>Formulated Raster</Description><Category>Data Type</Category><FactoryCLSID xsi:type='typens:UID'><UID xsi:type='xs:string'>{E001DEFC-E935-4000-8B3B-CE497A5BD87C}</UID></FactoryCLSID></ArrayOfGPDataTypeName><ArrayOfGPDataTypeName xsi:type='typens:GPDataTypeName'><Name>DEFeatureClass</Name><DisplayName>Feature Class</DisplayName><Description>Feature Class</Description><Category>Data Type</Category><FactoryCLSID xsi:type='typens:UID'><UID xsi:type='xs:string'>{64A3EBFB-6DEC-45DF-86A5-5BE541C5DBB6}</UID></FactoryCLSID></ArrayOfGPDataTypeName><ArrayOfGPDataTypeName xsi:type='typens:GPDataTypeName'><Name>GPFeatureLayer</Name><DisplayName>Feature Layer</DisplayName><Description>Feature Layer</Description><Category>Data Type</Category><FactoryCLSID xsi:type='typens:UID'><UID xsi:type='xs:string'>{E41CFD44-5741-4F2B-8ACE-1A49E146D329}</UID></FactoryCLSID></ArrayOfGPDataTypeName><ArrayOfGPDataTypeName xsi:type='typens:GPDataTypeName'><Name>DETin</Name><DisplayName>TIN</DisplayName><Description>TIN</Description><Category>Data Type</Category><FactoryCLSID xsi:type='typens:UID'><UID xsi:type='xs:string'>{44CD92B0-D549-4ED6-B891-3C58A71BDA14}</UID></FactoryCLSID></ArrayOfGPDataTypeName></DataTypeArray><FieldTypeArray xsi:type='typens:ArrayOfString'><String>esriFieldTypeOID</String><String>esriFieldTypeSmallInteger</String><String>esriFieldTypeInteger</String><String>esriFieldTypeSingle</String><String>esriFieldTypeDouble</String><String>esriFieldTypeString</String><String>esriFieldTypeGeometry</String></FieldTypeArray><GeometryTypeArray xsi:type='typens:ArrayOfString'><String>esriGeometryPoint</String><String>esriGeometryPolygon</String><String>esriGeometryPolyline</String><String>esriGeometryMultipoint</String></GeometryTypeArray><CheckField>true</CheckField><DefaultFieldName></DefaultFieldName></GeoDataDomain></DataTypeName><DisplayOrder>2</DisplayOrder><ControlCLSID xsi:nil='true'/><ParamDependencyArray xsi:type='typens:ArrayOfString'></ParamDependencyArray></GPEnvironment></ArrayOfGPEnvironment>